pyreutil/__init__.py
pyreutil/__main__.py
pyreutil/cli.py
pyreutil/pyreutil.py
pyreutil/utils.py
pyreutil-0.0.4.dist-info/LICENSE.txt
pyreutil-0.0.4.dist-info/METADATA
pyreutil-0.0.4.dist-info/WHEEL
pyreutil-0.0.4.dist-info/entry_points.txt
pyreutil-0.0.4.dist-info/top_level.txt
pyreutil-0.0.4.dist-info/RECORD
