Metadata-Version: 2.1
Name: pyreutil
Version: 0.0.4
Summary: Pyreutil is a command line utility to bulk edit plain text files or filenames using regex.
Home-page: https://github.com/michsun/pyreutil
Author: Michelle Sun
Author-email: michelle.sun032@icloud.com
Classifier: Development Status :: 4 - Beta
Classifier: Programming Language :: Python :: 3
Classifier: Programming Language :: Python :: 3.8
Classifier: Programming Language :: Python :: 3.9
Classifier: License :: OSI Approved :: MIT License
Classifier: Operating System :: OS Independent
License-File: LICENSE.txt
